{
	"schemaVersion": 1,
	"id": "mclm_picknplace",
	"version": "${version}",
	"name": "Pick n' Place",
	"description": "Adds the Pickaxe and Place blocks from 23w13a_or_b.",
	"authors": [
		"MCLegoMan"
	],
	"contact": {
		"homepage": "https://github.com/MCLegoMan",
		"sources": "https://github.com/MCLegoMan/picknmix"
	},
	"license": "LGPL-3.0-or-later",
	"icon": "assets/mclm_picknplace/icon.png",
	"environment": "*",
	"entrypoints": {
		"main": [
			"com.mclegoman.mclm_picknplace.common.PickNPlace"
		]
	},
	"depends": {
		"fabricloader": ">=0.16.5",
		"minecraft": "~1.21.1",
		"java": ">=21",
		"fabric-api": "*"
	},
	"accessWidener" : "mclm_picknplace.accesswidener"
}